mkdocs_media_gallery/__init__.py
mkdocs_media_gallery/plugin.py
mkdocs_media_gallery/assets/gallery.css
mkdocs_media_gallery/assets/gallery.js
mkdocs_media_gallery/templates/gallery_category_page.html
mkdocs_media_gallery/templates/gallery_full.html
mkdocs_media_gallery/templates/gallery_preview.html
mkdocs_media_gallery/templates/youtube_gallery.html
mkdocs_media_gallery_plugin-1.0.0.dist-info/licenses/LICENSE
mkdocs_media_gallery_plugin-1.0.0.dist-info/METADATA
mkdocs_media_gallery_plugin-1.0.0.dist-info/WHEEL
mkdocs_media_gallery_plugin-1.0.0.dist-info/entry_points.txt
mkdocs_media_gallery_plugin-1.0.0.dist-info/top_level.txt
mkdocs_media_gallery_plugin-1.0.0.dist-info/RECORD
