Metadata-Version: 2.4
Name: mkdocs-media-gallery-plugin
Version: 1.0.0
Summary: MkDocs plugin providing media galleries with shortcodes
Author: APinchofDill
License-Expression: MIT
Project-URL: Homepage, https://github.com/APinchofDill/mkdocs-media-gallery-plugin
Keywords: mkdocs,image,gallery
Classifier: Programming Language :: Python :: 3
Classifier: Operating System :: OS Independent
Requires-Python: >=3.8
License-File: LICENSE
Requires-Dist: mkdocs>=1.5
Requires-Dist: jinja2>=3.0
Requires-Dist: pyyaml>=6.0
Requires-Dist: mkdocs-glightbox>=0.4.0
Dynamic: license-file
